liman_signal_processing/__init__.py
liman_signal_processing/config.py
liman_signal_processing/diagnostics/__init__.py
liman_signal_processing/diagnostics/current_diagnostics.py
liman_signal_processing/diagnostics/vibration_diagnostics.py
liman_signal_processing/signal_processing/__init__.py
liman_signal_processing/signal_processing/envelope_analysis.py
liman_signal_processing/signal_processing/frequency_analysis.py
liman_signal_processing/signal_processing/preprocessing.py
liman_signal_processing/signal_processing/time_analysis.py
liman_signal_processing/utils/__init__.py
liman_signal_processing/utils/async_s3_client.py
liman_signal_processing/utils/unit_conversion.py
liman_signal_processing/utils/repos/__init__.py
liman_signal_processing/utils/repos/events.py
liman_signal_processing/utils/schemas/__init__.py
liman_signal_processing/utils/schemas/events.py
tests/__init__.py
liman_signal_processing-0.2.7.dist-info/METADATA
liman_signal_processing-0.2.7.dist-info/WHEEL
liman_signal_processing-0.2.7.dist-info/top_level.txt
liman_signal_processing-0.2.7.dist-info/RECORD
